core_platform/__init__.py
core_platform/platform_dtos.py
core_platform/platform_types.py
core_platform/platform_utils.py
core_platform/py.typed
turintech_platform-1.1.5.dist-info/METADATA
turintech_platform-1.1.5.dist-info/WHEEL
turintech_platform-1.1.5.dist-info/licenses/LICENSE
turintech_platform-1.1.5.dist-info/RECORD
