Metadata-Version: 2.4
Name: turintech_platform
Version: 1.1.5
Summary: Utils for platform information (system and machine architecture)
License-Expression: LicenseRef-Turing-Intelligence-Technology-EULA
License-File: LICENSE
Classifier: Development Status :: 5 - Production/Stable
Classifier: License :: Other/Proprietary License
Requires-Python: <3.14,>=3.11
